{"options":{},"indexes":[{"v":{"$numberInt":"2"},"key":{"_id":{"$numberInt":"1"}},"name":"_id_","ns":"grocery-user-service.products"},{"v":{"$numberInt":"2"},"key":{"business_category_id":{"$numberInt":"1"}},"name":"business_category_id_1","ns":"grocery-user-service.products","sparse":true,"background":true},{"v":{"$numberInt":"2"},"key":{"category_id":{"$numberInt":"1"}},"name":"category_id_1","ns":"grocery-user-service.products","sparse":true,"background":true},{"v":{"$numberInt":"2"},"key":{"sub_category_id":{"$numberInt":"1"}},"name":"sub_category_id_1","ns":"grocery-user-service.products","sparse":true,"background":true}],"uuid":"b7e2cbb9d5404766a8227ef5164b9093"}